find_ida_user_dir.py
find_ida_user_dir-0.3.0.dist-info/METADATA
find_ida_user_dir-0.3.0.dist-info/RECORD
find_ida_user_dir-0.3.0.dist-info/WHEEL
find_ida_user_dir-0.3.0.dist-info/entry_points.txt
find_ida_user_dir-0.3.0.dist-info/top_level.txt
