Metadata-Version: 2.1
Name: find-ida-user-dir
Version: 0.3.0
Summary: Find the user directory for IDA Pro in a platform-independent way
Home-page: https://github.com/Whatang/find_ida_user_dir
Author: Mike Thomas
Author-email: ida@whatang.org
License: GPLv3
Keywords: IDA
Platform: UNKNOWN
Classifier: Programming Language :: Python :: 2
Classifier: License :: OSI Approved :: GNU General Public License v3 (GPLv3)
Classifier: Operating System :: OS Independent
Classifier: Topic :: Software Development :: Disassemblers
Requires-Dist: click
